optimflow/__init__.py
optimflow/optimisation_parameters.py
optimflow/param_iter.py
optimflow/parameter_space.py
optimflow/simulation_parameters.py
optimflow/utils.py
optimflow-0.0.4.dist-info/licenses/LICENSE
optimflow-0.0.4.dist-info/METADATA
optimflow-0.0.4.dist-info/WHEEL
optimflow-0.0.4.dist-info/top_level.txt
optimflow-0.0.4.dist-info/RECORD
