Metadata-Version: 2.4
Name: optimflow
Version: 0.0.4
Requires-Python: >=3.9
License-File: LICENSE
Requires-Dist: matplotlib
Requires-Dist: pandas
Requires-Dist: param
Requires-Dist: pymoo
Requires-Dist: smt
Requires-Dist: ipykernel
Dynamic: license-file
